scdeepinsight/__init__.py
scdeepinsight/pbmc.py
scdeepinsight/pretrained_files_pbmc/checkpoint_model_pbmc.pth
scdeepinsight/pretrained_files_pbmc/img_transformer_pbmc.obj
scdeepinsight/pretrained_files_pbmc/label_encoder_pbmc.obj
scdeepinsight/pretrained_files_pbmc/pretrained_genes_pbmc.csv
scdeepinsight-2.3.2.dist-info/METADATA
scdeepinsight-2.3.2.dist-info/WHEEL
scdeepinsight-2.3.2.dist-info/RECORD
