Metadata-Version: 2.1
Name: scdeepinsight
Version: 2.3.2
Summary: An automatic cell type annotation tool for PBMC scRNA-seq data.
License: MIT
Author: Shangru JIA
Author-email: jiashangru@g.ecc.u-tokyo.ac.jp
Requires-Python: >=3.9,<4.0
Classifier: License :: OSI Approved :: MIT License
Classifier: Programming Language :: Python :: 3
Classifier: Programming Language :: Python :: 3.9
Classifier: Programming Language :: Python :: 3.10
Classifier: Programming Language :: Python :: 3.11
Requires-Dist: anndata (>=0.9.1,<0.10.0)
Requires-Dist: efficientnet-pytorch (>=0.7.1,<0.8.0)
Requires-Dist: numpy (>=1.24.3,<2.0.0)
Requires-Dist: pandas (>=2.0.2,<3.0.0)
Requires-Dist: pathlib (>=1.0.1,<2.0.0)
Requires-Dist: scanpy (>=1.9.3,<2.0.0)
Requires-Dist: scikit-learn (>=1.1.1,<2.0.0)
Requires-Dist: torch (>=2.0.0,<3.0.0)
Requires-Dist: torchvision (>=0.15.0,<0.16.0)
